teleput_cli/__init__.py
teleput_cli/teleput.py
teleput-0.1.dist-info/LICENSE.md
teleput-0.1.dist-info/METADATA
teleput-0.1.dist-info/WHEEL
teleput-0.1.dist-info/entry_points.txt
teleput-0.1.dist-info/top_level.txt
teleput-0.1.dist-info/RECORD
