Metadata-Version: 2.1
Name: teleput
Version: 0.1
Summary: Send text and files to the Teleput Telegram Bot
Home-page: https://github.com/Zverik/teleput-cli
Author: Ilya Zverev
Author-email: ilya@zverev.info
License: UNKNOWN
Platform: UNKNOWN
Classifier: Development Status :: 4 - Beta
Classifier: Environment :: Console
Classifier: Intended Audience :: Information Technology
Classifier: Intended Audience :: Customer Service
Classifier: Operating System :: OS Independent
Classifier: Topic :: Communications :: Chat
Classifier: License :: OSI Approved :: ISC License (ISCL)
Classifier: Programming Language :: Python :: 3 :: Only
Requires-Python: >=3.5
Requires-Dist: requests
Requires-Dist: appdirs
Requires-Dist: python-magic
